spectacle/__init__.py
spectacle/_astropy_init.py
spectacle/conftest.py
spectacle/version.py
spectacle/analysis/__init__.py
spectacle/analysis/region_finder.py
spectacle/analysis/resample.py
spectacle/analysis/statistics.py
spectacle/data/README.rst
spectacle/data/atoms.ecsv
spectacle/data/cos_lsf.ecsv
spectacle/extern/__init__.py
spectacle/fitting/__init__.py
spectacle/fitting/basin_hopper.py
spectacle/fitting/curve_fitter.py
spectacle/fitting/line_finder.py
spectacle/fitting/mcmc_fitter.py
spectacle/modeling/__init__.py
spectacle/modeling/converters.py
spectacle/modeling/lsfs.py
spectacle/modeling/models.py
spectacle/modeling/profiles.py
spectacle/registries/__init__.py
spectacle/registries/lines.py
spectacle/tests/__init__.py
spectacle/tests/coveragerc
spectacle/tests/setup_package.py
spectacle/tests/test_fitting.py
spectacle/tests/test_line_finder.py
spectacle/tests/test_model.py
spectacle/tests/test_modeling.py
spectacle/tests/test_resample.py
spectacle/tests/test_statistics.py
spectacle/utils/__init__.py
spectacle/utils/detection.py
spectacle/utils/misc.py
spectacle/utils/spelling_corrector.py
spectacle/utils/tests/__init__.py
spectacle-0.4.1.dist-info/METADATA
spectacle-0.4.1.dist-info/WHEEL
spectacle-0.4.1.dist-info/entry_points.txt
spectacle-0.4.1.dist-info/top_level.txt
spectacle-0.4.1.dist-info/RECORD
