Metadata-Version: 2.1
Name: spectacle
Version: 0.4.1
Summary: Modeling and analysis package for spectroscopic data.
Home-page: http://github.com/misty-pipeline/spectacle
Author: Nicholas Earl, Molly Peeples
Author-email: contact@nicholasearl.me
License: BSD 3-Clause
Platform: UNKNOWN
Requires-Python: >=3.6
Requires-Dist: astropy (<4.0)
Requires-Dist: specutils (>=0.4)
Requires-Dist: emcee (>=3.0rc2)
Requires-Dist: pyyaml
Requires-Dist: pathos
Requires-Dist: matplotlib
